setup.py
cratis_common/__init__.py
cratis_common/features.py
django_cratis_common.egg-info/PKG-INFO
django_cratis_common.egg-info/SOURCES.txt
django_cratis_common.egg-info/dependency_links.txt
django_cratis_common.egg-info/requires.txt
django_cratis_common.egg-info/top_level.txt