Metadata-Version: 1.0
Name: django-cratis-common
Version: 0.1.0
Summary: Integrates django admin
Home-page: UNKNOWN
Author: Alex Rudakov
Author-email: ribozz@gmail.com
License: MIT
Platform: UNKNOWN
